{
  "ADVr_SLT": {
    "long_name": "Vertical   Advective Flux of Salinity", 
    "units": "psu.m^3/s"
  }, 
  "ADVr_TH": {
    "long_name": "Vertical   Advective Flux of Pot.Temperature", 
    "units": "degC.m^3/s"
  }, 
  "ADVxHEFF": {
    "long_name": "Zonal      Advective Flux of eff ice thickn", 
    "units": "m.m^2/s"
  }, 
  "ADVxSNOW": {
    "long_name": "Zonal      Advective Flux of eff snow thickn", 
    "units": "m.m^2/s"
  }, 
  "ADVx_SLT": {
    "long_name": "Zonal      Advective Flux of Salinity", 
    "units": "psu.m^3/s"
  }, 
  "ADVx_TH": {
    "long_name": "Zonal      Advective Flux of Pot.Temperature", 
    "units": "degC.m^3/s"
  }, 
  "ADVyHEFF": {
    "long_name": "Meridional Advective Flux of eff ice thickn", 
    "units": "m.m^2/s"
  }, 
  "ADVySNOW": {
    "long_name": "Meridional Advective Flux of eff snow thickn", 
    "units": "m.m^2/s"
  }, 
  "ADVy_SLT": {
    "long_name": "Meridional Advective Flux of Salinity", 
    "units": "psu.m^3/s"
  }, 
  "ADVy_TH": {
    "long_name": "Meridional Advective Flux of Pot.Temperature", 
    "units": "degC.m^3/s"
  }, 
  "DETADT2": {
    "long_name": "Square of Surface Height Anomaly Tendency", 
    "units": "m^2/s^2"
  }, 
  "DFrE_SLT": {
    "long_name": "Vertical Diffusive Flux of Salinity    (Explicit part)", 
    "units": "psu.m^3/s"
  }, 
  "DFrE_TH": {
    "long_name": "Vertical Diffusive Flux of Pot.Temperature (Explicit part)", 
    "units": "degC.m^3/s"
  }, 
  "DFrI_SLT": {
    "long_name": "Vertical Diffusive Flux of Salinity    (Implicit part)", 
    "units": "psu.m^3/s"
  }, 
  "DFrI_TH": {
    "long_name": "Vertical Diffusive Flux of Pot.Temperature (Implicit part)", 
    "units": "degC.m^3/s"
  }, 
  "DFxEHEFF": {
    "long_name": "Zonal      Diffusive Flux of eff ice thickn", 
    "units": "m.m^2/s"
  }, 
  "DFxESNOW": {
    "long_name": "Zonal      Diffusive Flux of eff snow thickn", 
    "units": "m.m^2/s"
  }, 
  "DFxE_SLT": {
    "long_name": "Zonal      Diffusive Flux of Salinity", 
    "units": "psu.m^3/s"
  }, 
  "DFxE_TH": {
    "long_name": "Zonal      Diffusive Flux of Pot.Temperature", 
    "units": "degC.m^3/s"
  }, 
  "DFyEHEFF": {
    "long_name": "Meridional Diffusive Flux of eff ice thickn", 
    "units": "m.m^2/s"
  }, 
  "DFyESNOW": {
    "long_name": "Meridional Diffusive Flux of eff snow thickn", 
    "units": "m.m^2/s"
  }, 
  "DFyE_SLT": {
    "long_name": "Meridional Diffusive Flux of Salinity", 
    "units": "psu.m^3/s"
  }, 
  "DFyE_TH": {
    "long_name": "Meridional Diffusive Flux of Pot.Temperature", 
    "units": "degC.m^3/s"
  }, 
  "DRHODR": {
    "long_name": "Stratification: d.Sigma/dr (kg/m3/r_unit)", 
    "units": "kg/m^4"
  }, 
  "ETAN": {
    "long_name": "Surface Height Anomaly", 
    "standard_name": "sea_surface_height", 
    "units": "m"
  }, 
  "EVEL": {
    "long_name": "Eastward Component of Velocity (m/s)", 
    "standard_name": "eastward_sea_water_velocity", 
    "units": "m/s"
  }, 
  "EVELMASS": {
    "long_name": "Eastward Geometry-Weighted Comp of Velocity (m/s)", 
    "units": "m/s"
  }, 
  "EVELSTAR": {
    "long_name": "Eastward Component of Bolus Velocity (m/s)", 
    "standard_name": "eastward_sea_water_velocity_due_to_parameterized_mesoscale_eddies", 
    "units": "m/s"
  }, 
  "GM_PsiX": {
    "long_name": "GM Bolus transport stream-function : U component", 
    "units": "m^2/s"
  }, 
  "GM_PsiY": {
    "long_name": "GM Bolus transport stream-function : V component", 
    "units": "m^2/s"
  }, 
  "MXLDEPTH": {
    "long_name": "Mixed-Layer Depth (>0)", 
    "standard_name": "ocean_mixed_layer_thickness", 
    "units": "m"
  }, 
  "NVEL": {
    "long_name": "Northward Component of Velocity (m/s)", 
    "standard_name": "northward_sea_water_velocity", 
    "units": "m/s"
  }, 
  "NVELMASS": {
    "long_name": "Northward Geometry-Weighted Comp of Velocity (m/s)", 
    "units": "m/s"
  }, 
  "NVELSTAR": {
    "long_name": "Northward Component of Bolus Velocity (m/s)", 
    "standard_name": "northward_sea_water_velocity_due_to_parameterized_mesoscale_eddies", 
    "units": "m/s"
  }, 
  "OBP": {
    "long_name": "Ocean Bottom Pressure adjusted for global steric height change", 
    "units": "m"
  }, 
  "OBPNOPAB": {
    "long_name": "OBP with Global Mean Air-Pressure Removed",
    "units": "m"
  }, 
  "PHIBOT": {
    "long_name": "Bottom Pressure Pot.(p/rho) Anomaly", 
    "units": "m^2/s^2"
  }, 
  "PHIHYD": {
    "long_name": "Hydrostatic Pressure Pot.(p/rho) Anomaly", 
    "units": "m^2/s^2"
  }, 
  "RHOAnoma": {
    "long_name": "Density Anomaly (=Rho-rhoConst)", 
    "units": "kg/m^3"
  }, 
  "SALT": {
    "long_name": "Salinity", 
    "standard_name": "sea_water_salinity", 
    "units": "psu"
  }, 
  "SFLUX": {
    "long_name": "total salt flux (match salt-content variations), >0 increases salt", 
    "units": "g/m^2/s"
  }, 
  "SIacSubl": {
    "long_name": "Actual sublimation freshwater flux, >0 decr. ice", 
    "units": "kg/m^2/s"
  }, 
  "SIarea": {
    "long_name": "SEAICE fractional ice-covered area [0 to 1]", 
    "standard_name": "sea_ice_area_fraction", 
    "units": "1"
  }, 
  "SIatmFW": {
    "long_name": "Net freshwater flux from atmosphere & land (+=down)", 
    "units": "kg/m^2/s"
  }, 
  "SIatmQnt": {
    "long_name": "Net atmospheric heat flux, >0 decreases theta", 
    "standard_name": "surface_downward_heat_flux_in_air", 
    "units": "W/m^2"
  }, 
  "SIheff": {
    "long_name": "SEAICE effective ice thickness (avg. within grid cell)", 
    "standard_name": "sea_ice_thickness", 
    "units": "m"
  }, 
  "SIhsnow": {
    "long_name": "SEAICE effective snow thickness (avg. within grid cell)", 
    "standard_name": "surface_snow_thickness", 
    "units": "m"
  }, 
  "SIsnPrcp": {
    "long_name": "Snow precip. (+=dw) over Sea-Ice (area weighted)", 
    "standard_name": "snowfall_flux", 
    "units": "kg/m^2/s"
  }, 
  "SItflux": {
    "long_name": "Same as TFLUX but incl seaice (>0 incr T decr H)", 
    "units": "W/m^2"
  }, 
  "SIuice": {
    "long_name": "SEAICE x-dir. ice velocity (m/s)",
    "units": "m/s"
  }, 
  "SIvice": {
    "long_name": "SEAICE y-dir. ice velocity (m/s)", 
    "units": "m/s"
  }, 
  "SSH": {
    "long_name": "Surface Height Anomaly adjusted with global steric height change and sea-ice load", 
    "standard_name": "sea_surface_height", 
    "units": "m"
  }, 
  "SSHIB": {
    "long_name": "Inverted Barometer SSH", 
    "units": "m"
  }, 
  "SSHDYN": {
    "long_name": "Dynamic SSH (SSH-SSHIB)", 
    "units": "m"
  }, 
  "TFLUX": {
    "long_name": "total heat flux (match heat-content variations), >0 increases theta", 
    "units": "W/m^2"
  }, 
  "THETA": {
    "long_name": "Potential Temperature", 
    "standard_name": "sea_water_potential_temperature", 
    "units": "degC"
  }, 
  "UVEL": {
    "long_name": "X-Comp of Velocity (m/s) (not necessary eastward)", 
    "units": "m/s"
  }, 
  "UVELMASS": {
    "long_name": "X-Comp of Geometry-Weighted Velocity (m/s)", 
    "units": "m/s"
  }, 
  "UVELSTAR": {
    "long_name": "X-Comp of Bolus Velocity (m/s) weighted by hFacW", 
    "units": "m/s"
  }, 
  "VVEL": {
    "long_name": "Y-Comp of Velocity (m/s) (not necessary northward)", 
    "units": "m/s"
  }, 
  "VVELMASS": {
    "long_name": "Y-Comp of Geometry-Weighted Velocity (m/s)", 
    "units": "m/s"
  }, 
  "VVELSTAR": {
    "long_name": "Y-Comp of Bolus Velocity (m/s) weighted by hFacS", 
    "units": "m/s"
  }, 
  "WVELMASS": {
    "long_name": "Vertical Comp of Velocity (m/s)", 
    "standard_name": "upward_sea_water_velocity", 
    "units": "m/s"
  }, 
  "WVELSTAR": {
    "long_name": "Vertical Component of Bolus Velocity (r_units/s)", 
    "standard_name": "upward_sea_water_velocity_due_to_parameterized_mesoscale_eddies", 
    "units": "m/s"
  }, 
  "oceFWflx": {
    "long_name": "net surface Fresh-Water flux into the ocean (+=down), >0 decreases salinity", 
    "standard_name": "water_flux_into_sea_water", 
    "units": "kg/m^2/s"
  }, 
  "oceQnet": {
    "long_name": "net surface heat flux into the ocean (+=down), >0 increases theta", 
    "units": "W/m^2"
  }, 
  "oceQsw": {
    "long_name": "net Short-Wave radiation (+=down), >0 increases theta", 
    "standard_name": "net_downward_shortwave_flux_at_sea_water_surface", 
    "units": "W/m^2"
  }, 
  "oceSPDep": {
    "long_name": "Salt plume depth based on density criterion (>0)", 
    "units": "m"
  }, 
  "oceSPflx": {
    "long_name": "net surface Salt flux rejected into the ocean during freezing, (+=down),", 
    "units": "g/m^2/s"
  }, 
  "oceSPtnd": {
    "long_name": "salt tendency due to salt plume flux >0 increases salinity", 
    "units": "g/m^2/s"
  }, 
  "oceTAUE": {
    "long_name": "eastward surface wind stress, >0 increases eVel",
    "units": "Pa"
  }, 
  "oceTAUN": {
    "long_name": "northward surf. wind stress, >0 increases nVel",
    "units": "Pa"
  }, 
  "oceTAUX": {
    "long_name": "zonal surface wind stress, >0 increases uVel", 
    "standard_name": "surface_downward_x_stress", 
    "units": "Pa"
  }, 
  "oceTAUY": {
    "long_name": "meridional surface wind stress, >0 increases vVel", 
    "standard_name": "surface_downward_y_stress", 
    "units": "Pa"
  }, 
  "sIceLoad": {
    "long_name": "sea-ice loading (in Mass of ice+snow / area unit)", 
    "standard_name": "sea_ice_and_surface_snow_amount", 
    "units": "kg/m^2"
  },
  "Depth": {
    "long_name": "ocean depth",
    "standard_name": "sea_floor_depth",
    "units": "m"
  },
  "YC": {
    "valid_range": "-90., 90.", 
    "long_name": "latitude at center of tracer cell", 
    "units": "degrees_north"
  },  
  "YG": {
    "valid_range": "-90., 90.", 
    "long_name": "latitude at tracer face", 
    "units": "degrees_north"
  },  
  "XC": {
    "valid_range": "-180., 180.", 
    "long_name": "longitude at center of tracer cell", 
    "units": "degrees_east"
  }, 
  "XG": {
    "valid_range": "-180., 180.", 
    "long_name": "longitude at tracer face", 
    "units": "degrees_east"
  },
  "rA": {
    "long_name": "tracer cell area",
    "units": "m^2"
  },
  "rAs": {
    "long_name": "cell area at s location",
    "units": "m^2"
  },
  "rAw": {
    "long_name": "cell area at w location",
    "units": "m^2"
  },
  "rAz": {
    "long_name": "cell area at z location",
    "units": "m^2"
  },
  "CS": {
    "long_name": "cosine of grid orientation angle",
    "units": "1"
  },
  "SN": {
    "long_name": "sine of grid orientation angle",
    "units": "1"
  }

}
